odoo8_addon_purchase_update_proposal-8.0.0.2.0-py3.8-nspkg.pth
odoo_addons/purchase_update_proposal/README.rst
odoo_addons/purchase_update_proposal/__init__.py
odoo_addons/purchase_update_proposal/__openerp__.py
odoo_addons/purchase_update_proposal/demo/demo.xml
odoo_addons/purchase_update_proposal/i18n/fr.po
odoo_addons/purchase_update_proposal/i18n/purchase_update_proposal.pot
odoo_addons/purchase_update_proposal/models/__init__.py
odoo_addons/purchase_update_proposal/models/partner.py
odoo_addons/purchase_update_proposal/models/purchase_order.py
odoo_addons/purchase_update_proposal/models/purchase_order_line.py
odoo_addons/purchase_update_proposal/models/purchase_proposal.py
odoo_addons/purchase_update_proposal/readme/AUTHOR.rst
odoo_addons/purchase_update_proposal/readme/DESCRIPTION.rst
odoo_addons/purchase_update_proposal/readme/USAGE.rst
odoo_addons/purchase_update_proposal/security/ir.model.access.csv
odoo_addons/purchase_update_proposal/security/security.xml
odoo_addons/purchase_update_proposal/static/description/icon.png
odoo_addons/purchase_update_proposal/static/description/index.html
odoo_addons/purchase_update_proposal/static/description/purchaser.png
odoo_addons/purchase_update_proposal/static/description/supplier.png
odoo_addons/purchase_update_proposal/tests/__init__.py
odoo_addons/purchase_update_proposal/tests/test_proposal.py
odoo_addons/purchase_update_proposal/tests/test_proposal_with_picking.py
odoo_addons/purchase_update_proposal/views/partner.xml
odoo_addons/purchase_update_proposal/views/purchase_line_proposal.xml
odoo_addons/purchase_update_proposal/views/purchase_order.xml
odoo_addons/purchase_update_proposal/views/supplier_purchase_order.xml
odoo8_addon_purchase_update_proposal-8.0.0.2.0.dist-info/METADATA
odoo8_addon_purchase_update_proposal-8.0.0.2.0.dist-info/WHEEL
odoo8_addon_purchase_update_proposal-8.0.0.2.0.dist-info/namespace_packages.txt
odoo8_addon_purchase_update_proposal-8.0.0.2.0.dist-info/top_level.txt
odoo8_addon_purchase_update_proposal-8.0.0.2.0.dist-info/RECORD
