Metadata-Version: 2.1
Name: odoo8-addon-purchase-update-proposal
Version: 8.0.0.2.0
Summary: Allow to define alternate quantity, date on lines
Home-page: UNKNOWN
Author: Akretion,Odoo Community Association (OCA)
Author-email: support@odoo-community.org
License: AGPL-3
Platform: UNKNOWN
Classifier: Programming Language :: Python
Classifier: Framework :: Odoo
Classifier: Framework :: Odoo :: 8.0
Classifier: License :: OSI Approved :: GNU Affero General Public License v3
Classifier: Development Status :: 3 - Alpha
Requires-Python: ~=2.7
Requires-Dist: odoo (<9.0a,>=8.0a)
